[
  {
    "timestamp": "02/08/2021 01:17 AM",
    "title": "Mỹ nhân Hoa ngữ \"cưa sừng làm nghé\" hóa nữ sinh: Nhiệt Ba - Trịnh Sảng trẻ trung ngỡ ngàng, \"trùm cuối\" là cao thủ hack tuổi",
    "description": "Nhiều mỹ nhân Hoa ngữ khiến khán giả ngỡ ngàng bởi vẻ trẻ trung và trong sáng khi vào vai nữ sinh.",
    "src": "https://kenh14cdn.com/thumb_w/660/203336854389633024/2021/7/27/33-1627371707185415933730.jpg",
    "alt": "Địch Lệ Nhiệt Ba,Dương Mịch,Lưu Thi Thi,Lưu Diệc Phi,Trịnh Sảng,Trần Nghiên Hy,đàm tùng vận,Mỹ nhân Hoa ngữ,",
    "category": "stars",
    "date": "02/08/2021",
    "time": "01:17 AM",
    "link": "/my-nhan-hoa-ngu-cua-sung-lam-nghe-hoa-nu-sinh-nhiet-ba-trinh-sang-tre-trung-ngo-ngang-trum-cuoi-la-cao-thu-hack-tuoi",
    "zcomponent": "page_20210802011700",
    "filepath": "./20210802011700-my-nhan-hoa-ngu-cua-sung-lam-nghe-hoa-nu-sinh-nhiet-ba-trinh-sang-tre-trung-ngo-ngang-trum-cuoi-la-cao-thu-hack-tuoi.js"
  },
  {
    "timestamp": "02/08/2021 01:17 AM",
    "title": "Ngay trong đêm Khang Hy băng hà, Ung Chính lập tức xử tử thân tín đã theo tiên đế suốt 60 năm, ông đến cùng đã đắc tội với ai?",
    "description": "Lý do thực sự khiến Ung Chính xử tử Triệu Xương - một thái giám cận kề hơn 60 năm bên Khang Hy đế ngay trong đêm ông băng hà là gì?",
    "src": "https://kenh14cdn.com/thumb_w/620/203336854389633024/2021/7/26/-16272921001512030615251.jpg",
    "alt": "nhà Thanh Trung Quốc,Uông Chính,khang hy,",
    "category": "news",
    "date": "02/08/2021",
    "time": "01:17 AM",
    "link": "/ngay-trong-dem-khang-hy-bang-ha-ung-chinh-lap-tuc-xu-tu-than-tin-da-theo-tien-de-suot-60-nam-ong-den-cung-da-dac-toi-voi-ai",
    "zcomponent": "page_20210802011714",
    "filepath": "./20210802011714-ngay-trong-dem-khang-hy-bang-ha-ung-chinh-lap-tuc-xu-tu-than-tin-da-theo-tien-de-suot-60-nam-ong-den-cung-da-dac-toi-voi-ai.js"
  },
  {
    "timestamp": "02/08/2021 01:17 AM",
    "title": "Triệu Lệ Dĩnh thật sự \"nặng nợ\" với giày dép!",
    "description": "Vốn có tạng người nhỏ bé, đặc biệt là đôi chân nhỏ nên Triệu Lệ Dĩnh cũng gặp nhiều khó khăn khi chọn giày dép.",
    "src": "https://kenh14cdn.com/thumb_w/660/203336854389633024/2021/8/1/photo-1-16272214927271347365146-1627272206890982067480-16278016114931281461667.jpeg",
    "alt": "triệu lệ dĩnh,sao Trung,sao Hoa ngữ,star style,giày cao gót,boot,sao mặc gì,giày rộng,",
    "category": "stars",
    "date": "02/08/2021",
    "time": "01:17 AM",
    "link": "/trieu-le-dinh-that-su-nang-no-voi-giay-dep",
    "zcomponent": "page_20210802011723",
    "filepath": "./20210802011723-trieu-le-dinh-that-su-nang-no-voi-giay-dep.js"
  },
  {
    "timestamp": "02/08/2021 01:17 AM",
    "title": "Tại sao các huấn luyện viên chỉ dùng 6 Pokémon mà thôi?",
    "description": "Con số 6 được coi là chuẩn hóa với các huấn luyện viên Pokémon kể từ đầu khi mới khai sinh ra game cho tới thời điểm hiện tại.",
    "src": "https://gamek.mediacdn.vn/133514250583805952/2021/7/31/photo-1-16277492905702081276162.png",
    "alt": "POKÉMON,",
    "category": "games",
    "date": "02/08/2021",
    "time": "01:17 AM",
    "link": "/tai-sao-cac-huan-luyen-vien-chi-dung-6-pokemon-ma-thoi",
    "zcomponent": "page_20210802011740",
    "filepath": "./20210802011740-tai-sao-cac-huan-luyen-vien-chi-dung-6-pokemon-ma-thoi.js"
  },
  {
    "timestamp": "02/08/2021 01:17 AM",
    "title": "12 game NFT có thể kiếm tiền \"ngon\" như Axie Infinity (Phần 1)",
    "description": "Game NFT đã khởi đầu cho xu hướng chơi game kiếm tiền đang thịnh hành trên thế giới.",
    "src": "https://gamek.mediacdn.vn/thumb_w/640/133514250583805952/2021/7/31/photo-1-16277432005911663617292.jpg",
    "alt": "AXIE INFINITY,GAME NFT,CHƠI GAME KIẾM TIỀN,PLAY TO EARN,TIỀN ẢO,AXS,SLP,",
    "category": "games",
    "date": "02/08/2021",
    "time": "01:17 AM",
    "link": "/12-game-nft-co-the-kiem-tien-ngon-nhu-axie-infinity-phan-1",
    "zcomponent": "page_20210802011748",
    "filepath": "./20210802011748-12-game-nft-co-the-kiem-tien-ngon-nhu-axie-infinity-phan-1.js"
  },
  {
    "timestamp": "02/08/2021 01:18 AM",
    "title": "Top 10 tựa game PC những năm 2000 với đồ họa đỉnh cao làm game thủ mãi nhớ (P.2)",
    "description": "Những ấn tượng không thể nào quên với các anh em game thủ 8x 9x một thời.",
    "src": "https://gamek.mediacdn.vn/thumb_w/640/133514250583805952/2021/8/1/photo-1-1627755900498830370556.png",
    "alt": "GAME,GAME HAY,GAME ĐỈNH,CỘNG ĐỒNG MẠNG,TIN TỨC GAME,ĐỒ HỌA GAME,",
    "category": "games",
    "date": "02/08/2021",
    "time": "01:18 AM",
    "link": "/top-10-tua-game-pc-nhung-nam-2000-voi-do-hoa-dinh-cao-lam-game-thu-mai-nho-p2",
    "zcomponent": "page_20210802011803",
    "filepath": "./20210802011803-top-10-tua-game-pc-nhung-nam-2000-voi-do-hoa-dinh-cao-lam-game-thu-mai-nho-p2.js"
  },
  {
    "timestamp": "02/08/2021 01:18 AM",
    "title": "Những điều ngớ ngẩn game thủ thường gặp trong open world game",
    "description": "Dù open world game được xây dựng với mục tiêu mô phỏng lại thế giới thực càng giống càng tốt, nhưng vẫn có những chi tiết cực kỳ ngớ ngẩn tồn tại trong phần lớn các tựa game.",
    "src": "https://gamek.mediacdn.vn/133514250583805952/2021/7/29/-16275505649941752679599.jpg",
    "alt": "KHÁM PHÁ,GAME OPEN WORLD,GAME ONLINE,TRÒ CHƠI ĐIỆN TỬ,GIẢI TRÍ,",
    "category": "games",
    "date": "02/08/2021",
    "time": "01:18 AM",
    "link": "/nhung-dieu-ngo-ngan-game-thu-thuong-gap-trong-open-world-game",
    "zcomponent": "page_20210802011814",
    "filepath": "./20210802011814-nhung-dieu-ngo-ngan-game-thu-thuong-gap-trong-open-world-game.js"
  },
  {
    "timestamp": "02/08/2021 01:18 AM",
    "title": "Mặc áo trễ nải rồi làm \"rơi\" tâm hồn trên sóng, nữ streamer vô danh bỗng chốc hóa tân binh tiềm năng, được donate nhiệt liệt",
    "description": "Một hành động tưởng như vô tình, nhưng lại khiến cô nàng streamer trở nên nổi tiếng một cách khó lường.",
    "src": "https://gamek.mediacdn.vn/thumb_w/640/133514250583805952/2021/7/27/photo-1-1627364087502275971880.gif",
    "alt": "GÁI XINH,HOT GIRL,CỘNG ĐỒNG MẠNG,",
    "category": "images",
    "date": "02/08/2021",
    "time": "01:18 AM",
    "link": "/mac-ao-tre-nai-roi-lam-roi-tam-hon-tren-song-nu-streamer-vo-danh-bong-choc-hoa-tan-binh-tiem-nang-duoc-donate-nhiet-liet",
    "zcomponent": "page_20210802011826",
    "filepath": "./20210802011826-mac-ao-tre-nai-roi-lam-roi-tam-hon-tren-song-nu-streamer-vo-danh-bong-choc-hoa-tan-binh-tiem-nang-duoc-donate-nhiet-liet.js"
  },
  {
    "timestamp": "02/08/2021 01:18 AM",
    "title": "Giật mình khi thấy các mỹ nhân anime bất ngờ đi độ ngực, ai cũng có tâm hồn ngồn ngộn nhức mắt",
    "description": "Dù phụ nữ có da trắng đến cỡ nào, da mặt đẹp và dáng chuẩn đến bao nhiêu thì trong mắt đàn ông, vòng 1 vẫn là điểm họ dừng mắt đầu tiên và lâu nhất.",
    "src": "https://gamek.mediacdn.vn/thumb_w/640/133514250583805952/2021/7/31/photo-1-16277383453661718633477.jpg",
    "alt": "ANIME,MỸ NHÂN ANIME,VÒNG 1,TÂM HỒN PHỤ NỮ,MỸ NHÂN NGỰC KHỦNG,FAN ART,",
    "category": "games",
    "date": "02/08/2021",
    "time": "01:18 AM",
    "link": "/giat-minh-khi-thay-cac-my-nhan-anime-bat-ngo-di-do-nguc-ai-cung-co-tam-hon-ngon-ngon-nhuc-mat",
    "zcomponent": "page_20210802011846",
    "filepath": "./20210802011846-giat-minh-khi-thay-cac-my-nhan-anime-bat-ngo-di-do-nguc-ai-cung-co-tam-hon-ngon-ngon-nhuc-mat.js"
  },
  {
    "timestamp": "02/08/2021 01:18 AM",
    "title": "Cày phim ngày dịch, top 5 anime người máy - mecha siêu hấp dẫn sau đây sẽ kiến bạn hài lòng",
    "description": "Cùng chúng tôi đến với 5 anime người máy - mecha cực đỉnh giúp bạn giải trí trong những ngày ở nhà chống dịch này nhé!",
    "src": "https://gamek.mediacdn.vn/thumb_w/640/133514250583805952/2021/8/1/any1-16277975881851921103740.jpg",
    "alt": "SHOP ANIME - MANGA,PHONG CÁCH ANIME,TRAILER ANIME,MOVIE ANIME,REVIEW ANIME,ĐÁNH GIÁ ANIME,GAME ANIME,TV ANIME,MANGA ANIME,TOP ANIME,",
    "category": "games",
    "date": "02/08/2021",
    "time": "01:18 AM",
    "link": "/cay-phim-ngay-dich-top-5-anime-nguoi-may-mecha-sieu-hap-dan-sau-day-se-kien-ban-hai-long",
    "zcomponent": "page_20210802011854",
    "filepath": "./20210802011854-cay-phim-ngay-dich-top-5-anime-nguoi-may-mecha-sieu-hap-dan-sau-day-se-kien-ban-hai-long.js"
  },
  {
    "timestamp": "02/08/2021 01:19 AM",
    "title": "Top 10 Rồng thần \"ngầu\" nhất Dragon Ball: Con bay trên trời, con đi dưới đất, con dùng hẳn máy thời gian để \"săn lùng\" (P1)",
    "description": "Dragon Ball xuất hiện vô số phiên bản Rồng thần, mỗi con đều có những hình dạng và sức mạnh đặc biệt.",
    "src": "https://gamek.mediacdn.vn/thumb_w/640/133514250583805952/2021/8/1/anh-1-16278005780421511752096.jpg",
    "alt": "DRAGON BALL,7 VIÊN NGỌC RỒNG,RỒNG THẦN,SERIES DRAGON BALL,",
    "category": "games",
    "date": "02/08/2021",
    "time": "01:19 AM",
    "link": "/top-10-rong-than-ngau-nhat-dragon-ball-con-bay-tren-troi-con-di-duoi-dat-con-dung-han-may-thoi-gian-de-san-lung-p1",
    "zcomponent": "page_20210802011906",
    "filepath": "./20210802011906-top-10-rong-than-ngau-nhat-dragon-ball-con-bay-tren-troi-con-di-duoi-dat-con-dung-han-may-thoi-gian-de-san-lung-p1.js"
  },
  {
    "timestamp": "02/08/2021 01:19 AM",
    "title": "8 mẹo đơn giản để tăng tín hiệu sóng Wi-fi lên mức tối đa",
    "description": "Trong những ngày giãn cách xã hội, mạng Wi-fi là một trong những yếu tố quan trọng để học tập, làm việc và giải trí.",
    "src": "https://gamek.mediacdn.vn/133514250583805952/2021/8/1/photo-1-1627820158564578927919.jpg",
    "alt": "YẾU TỐ QUAN TRỌNG,TĂNG TỐC MẠNG WI-FI,WI-FI,SÓNG WI-FI,TĂNG TỐC MẠNG,TĂNG TỐC WI-FI,TÍN HIỆU WI-FI,",
    "category": "tech",
    "date": "02/08/2021",
    "time": "01:19 AM",
    "link": "/8-meo-don-gian-de-tang-tin-hieu-song-wi-fi-len-muc-toi-da",
    "zcomponent": "page_20210802011917",
    "filepath": "./20210802011917-8-meo-don-gian-de-tang-tin-hieu-song-wi-fi-len-muc-toi-da.js"
  },
  {
    "timestamp": "02/08/2021 01:19 AM",
    "title": "One Piece: Biến thành động vật và 3 đặc điểm của trái ác quỷ hệ Zoan khác hẳn những hệ khác",
    "description": "Người sở hữu năng lực trái ác quỷ hệ Zoan có khả năng biến thành một loài động vật, kèm theo đó là các đặc điểm cũng như khả năng của loài vật đó.",
    "src": "https://gamek.mediacdn.vn/thumb_w/640/133514250583805952/2021/8/1/photo-1-1627800104680345133960.jpg",
    "alt": "ONE PIECE,TRÁI ÁC QUỶ,TRÁI ZOAN,ZOAN CỔ ĐẠI,LOẠI TRÁI ÁC QUỶ,",
    "category": "games",
    "date": "02/08/2021",
    "time": "01:19 AM",
    "link": "/one-piece-bien-thanh-dong-vat-va-3-dac-diem-cua-trai-ac-quy-he-zoan-khac-han-nhung-he-khac",
    "zcomponent": "page_20210802011936",
    "filepath": "./20210802011936-one-piece-bien-thanh-dong-vat-va-3-dac-diem-cua-trai-ac-quy-he-zoan-khac-han-nhung-he-khac.js"
  },
  {
    "timestamp": "02/08/2021 01:20 AM",
    "title": "Mỹ nhân 18+ hé lộ mắc bệnh nghiêm trọng, than ngắn thở dài bỏ ngỏ việc giải nghệ",
    "description": "Aoi Tsubasa đã tâm sự về chuyện cô nàng mắc bệnh dạ dày, nhưng cuối cùng lại phát hiện thêm bệnh khác và phải trì hoãn việc đóng phim.",
    "src": "https://gamek.mediacdn.vn/133514250583805952/2021/8/1/photo-1-1627792620526175642758.jpg",
    "alt": "AOI TSUBASA,IDOL,",
    "category": "images",
    "date": "02/08/2021",
    "time": "01:20 AM",
    "link": "/my-nhan-18-he-lo-mac-benh-nghiem-trong-than-ngan-tho-dai-bo-ngo-viec-giai-nghe",
    "zcomponent": "page_20210802012044",
    "filepath": "./20210802012044-my-nhan-18-he-lo-mac-benh-nghiem-trong-than-ngan-tho-dai-bo-ngo-viec-giai-nghe.js"
  },
  {
    "timestamp": "02/08/2021 01:21 AM",
    "title": "Đại chiến bikini phiên bản ở nhà mùa dịch: Sao Việt lẫn gái xinh vẫn diện toàn đồ sexy rõ chiến, chị em nom thèm ra biển lắm rồi",
    "description": "Vẫn là trào lưu lên đồ ở nhà nhưng cục diện đã thay đổi khi chị đại Thanh Hằng khiến đàn em thơ phần nào bị lu mờ.",
    "src": "https://kenh14cdn.com/thumb_w/620/203336854389633024/2021/8/2/2288412615766622333288115516340885772097766n-16278676557721976941634.jpg",
    "alt": "show your best contest,show your best,estee lauder,nghỉ dịch,Gái đẹp đại chiến bikini,đồ bơi,thanh hằng,Kiều Ly Phạm,vợ Rhymastic,star style,Nhà Lên Đèn, Em Lên Đồ,",
    "category": "images",
    "date": "02/08/2021",
    "time": "01:21 AM",
    "link": "/dai-chien-bikini-phien-ban-o-nha-mua-dich-sao-viet-lan-gai-xinh-van-dien-toan-do-sexy-ro-chien-chi-em-nom-them-ra-bien-lam-roi",
    "zcomponent": "page_20210802012106",
    "filepath": "./20210802012106-dai-chien-bikini-phien-ban-o-nha-mua-dich-sao-viet-lan-gai-xinh-van-dien-toan-do-sexy-ro-chien-chi-em-nom-them-ra-bien-lam-roi.js"
  },
  {
    "timestamp": "02/08/2021 01:21 AM",
    "title": "Lọ Lem nhà MC Quyền Linh xinh thực sự, ở nhà mặc đồ bộ mà cũng có loạt ảnh \"tới công chuyện\"",
    "description": "Không xuất hiện trong những bộ váy nền nã, nữ tính thường thấy nhưng Lọ Lem vẫn khiến mọi người khen nức nở.",
    "src": "https://kenh14cdn.com/thumb_w/660/203336854389633024/2021/8/2/anh-chup-man-hinh-2021-08-02-luc-73949-sa-16278650239571095112497.png",
    "alt": "Lọ Lem,Con gái MC Quyền Linh,MC Quyền Linh,mai thảo linh,gái xinh,Hello GenZ,Nhà Lên Đèn, Em Lên Đồ,gái xinh gen Z,",
    "category": "stars",
    "date": "02/08/2021",
    "time": "01:21 AM",
    "link": "/lo-lem-nha-mc-quyen-linh-xinh-thuc-su-o-nha-mac-do-bo-ma-cung-co-loat-anh-toi-cong-chuyen",
    "zcomponent": "page_20210802012120",
    "filepath": "./20210802012120-lo-lem-nha-mc-quyen-linh-xinh-thuc-su-o-nha-mac-do-bo-ma-cung-co-loat-anh-toi-cong-chuyen.js"
  },
  {
    "timestamp": "02/08/2021 01:21 AM",
    "title": "Thả rông vòng một rồi bôi dầu bóng loáng khi lên sóng, nữ streamer khiến người xem sốc nặng khi cố tình hớ hênh \"điểm nhạy cảm\"",
    "description": "Số lượng án phạt cấm kênh mà cô nàng streamer này phải nhận chắc cũng chẳng thể đếm nổi nữa rồi.",
    "src": "https://kenh14cdn.com/thumb_w/620/203336854389633024/2021/8/2/photo-1-1627876511023130087944.jpg",
    "alt": "thả rông vòng một,điểm nhạy cảm,ứng cử viên,đồng nghiệp nam,phòng khách sạn,áo hai dây,Khoe thân phản cảm,streamer,",
    "category": "images",
    "date": "02/08/2021",
    "time": "01:21 AM",
    "link": "/tha-rong-vong-mot-roi-boi-dau-bong-loang-khi-len-song-nu-streamer-khien-nguoi-xem-soc-nang-khi-co-tinh-ho-henh-diem-nhay-cam",
    "zcomponent": "page_20210802012128",
    "filepath": "./20210802012128-tha-rong-vong-mot-roi-boi-dau-bong-loang-khi-len-song-nu-streamer-khien-nguoi-xem-soc-nang-khi-co-tinh-ho-henh-diem-nhay-cam.js"
  },
  {
    "timestamp": "02/08/2021 01:21 AM",
    "title": "12 game NFT có thể kiếm tiền \"ngon\" như Axie Infinity (Phần 2)",
    "description": "Mời các bạn tiếp tục đến với series những tựa game NFT hot nhất thị trường.",
    "src": "https://gamek.mediacdn.vn/thumb_w/640/133514250583805952/2021/8/1/photo-1-16278323277561900075355.jpg",
    "alt": "THẾ GIỚI ẢO,GAME NFT,CHƠI GAME KIẾM TIỀN,PLAY TO EARN,THẾ GIỚI MỞ,TIỀN ẢO,",
    "category": "games",
    "date": "02/08/2021",
    "time": "01:21 AM",
    "link": "/12-game-nft-co-the-kiem-tien-ngon-nhu-axie-infinity-phan-2",
    "zcomponent": "page_20210802012138",
    "filepath": "./20210802012138-12-game-nft-co-the-kiem-tien-ngon-nhu-axie-infinity-phan-2.js"
  },
  {
    "timestamp": "02/08/2021 01:21 AM",
    "title": "Xinh quá mức, hot girl tân binh phim 18+ chưa debut đã được kỳ vọng sẽ chấm dứt \"kỷ nguyên\" của Yua Mikami",
    "description": "Cô nàng hot girl này đang là một trong những chủ đề nóng nhất ở ngành công nghiệp phim 18+ thời điểm hiện tại.",
    "src": "https://gamek.mediacdn.vn/thumb_w/640/133514250583805952/2021/7/28/screenshot26-1627475768995824801854-16274757850181367325443-16274758003152076189091.png",
    "alt": "HOT GIRL,GÁI XINH,CỘNG ĐỒNG MẠNG,KAEDE,PHIM AV,PHIM 18+,AV,",
    "category": "images",
    "date": "02/08/2021",
    "time": "01:21 AM",
    "link": "/xinh-qua-muc-hot-girl-tan-binh-phim-18-chua-debut-da-duoc-ky-vong-se-cham-dut-ky-nguyen-cua-yua-mikami",
    "zcomponent": "page_20210802012148",
    "filepath": "./20210802012148-xinh-qua-muc-hot-girl-tan-binh-phim-18-chua-debut-da-duoc-ky-vong-se-cham-dut-ky-nguyen-cua-yua-mikami.js"
  },
  {
    "timestamp": "02/08/2021 01:22 AM",
    "title": "BXH diễn viên 18+ ăn khách 6/2021: Yua Mikami \"đánh rơi\" ngôi đầu, Eimi Fukada vẫn chìm nghỉm?",
    "description": "Việc Yua Mikami bỏ lỡ vị trí top 1 trong tháng 7 vừa qua là điều khá bất ngờ với nhiều người.",
    "src": "https://gamek.mediacdn.vn/thumb_w/640/133514250583805952/2021/8/2/photo-1-16278770679801776928089.png",
    "alt": "IDOL,YUA MIKAMI,BẢNG XẾP HẠNG,SAIKA KAWAKITA,EIMI FUKADA,",
    "category": "images",
    "date": "02/08/2021",
    "time": "01:22 AM",
    "link": "/bxh-dien-vien-18-an-khach-6-2021-yua-mikami-danh-roi-ngoi-dau-eimi-fukada-van-chim-nghim",
    "zcomponent": "page_20210802012203",
    "filepath": "./20210802012203-bxh-dien-vien-18-an-khach-6-2021-yua-mikami-danh-roi-ngoi-dau-eimi-fukada-van-chim-nghim.js"
  },
  {
    "timestamp": "02/08/2021 01:22 AM",
    "title": "Thương hiệu thời trang Louis Vuitton chuẩn bị ra mắt game NFT điện thoại",
    "description": "Không chỉ lấn sân sang ngành game, thương hiệu thời trang của Pháp cũng sẽ sử dụng luôn cả NFT.",
    "src": "https://gamek.mediacdn.vn/thumb_w/640/133514250583805952/2021/8/2/photo-1-16278756721141711018649.jpg",
    "alt": "THƯƠNG HIỆU THỜI TRANG,GAME NFT,NFT,TIỀN ẢO,BLOCKCHAIN,TRÒ CHƠI ĐIỆN TỬ,",
    "category": "games",
    "date": "02/08/2021",
    "time": "01:22 AM",
    "link": "/thuong-hieu-thoi-trang-louis-vuitton-chuan-bi-ra-mat-game-nft-dien-thoai",
    "zcomponent": "page_20210802012212",
    "filepath": "./20210802012212-thuong-hieu-thoi-trang-louis-vuitton-chuan-bi-ra-mat-game-nft-dien-thoai.js"
  },
  {
    "timestamp": "02/08/2021 01:22 AM",
    "title": "Đồng coin Axie Infinity rớt giá thảm hại, game thủ Việt náo loạn vì \"đu đỉnh\"",
    "description": "Game thủ Axie Infinity Việt Nam đang lo lắng vì giá tiền ảo của game liên tục giảm.",
    "src": "https://gamek.mediacdn.vn/133514250583805952/2021/8/2/3-16278792827231259436558-1627879302333166739249.png",
    "alt": "GAME THỦ VIỆT,GAME NFT,AXIE INFINITY,TIỀN ẢO,SLP,AXS,SLP COIN,",
    "category": "games",
    "date": "02/08/2021",
    "time": "01:22 AM",
    "link": "/dong-coin-axie-infinity-rot-gia-tham-hai-game-thu-viet-nao-loan-vi-du-dinh",
    "zcomponent": "page_20210802012221",
    "filepath": "./20210802012221-dong-coin-axie-infinity-rot-gia-tham-hai-game-thu-viet-nao-loan-vi-du-dinh.js"
  },
  {
    "timestamp": "02/08/2021 01:22 AM",
    "title": "Khai thật đi! Bạn đã từng đập chuột, bàn phím vì các nhiệm vụ huyền thoại, khó đến mức “phát điên” này chưa?",
    "description": "Có lẽ trong series GTA thì đây xứng đáng là chuỗi nhiệm vụ khó bậc nhất khiến người chơi vô cùng ức chế.",
    "src": "https://gamek.mediacdn.vn/thumb_w/640/133514250583805952/2021/8/1/photo-1-1627836247715331530341.jpg",
    "alt": "GTA,GTA VICE CITY,GTA SAN ANDREAS,TIN TỨC GAME,DEMOLITION MAN,",
    "category": "games",
    "date": "02/08/2021",
    "time": "01:22 AM",
    "link": "/khai-that-di-ban-da-tung-dap-chuot-ban-phim-vi-cac-nhiem-vu-huyen-thoai-kho-den-muc-phat-dien-nay-chua",
    "zcomponent": "page_20210802012229",
    "filepath": "./20210802012229-khai-that-di-ban-da-tung-dap-chuot-ban-phim-vi-cac-nhiem-vu-huyen-thoai-kho-den-muc-phat-dien-nay-chua.js"
  }
]
